fa_test_generator/__init__.py
fa_test_generator/fa_test_generator.py
fa_test_generator-0.1.3.dist-info/LICENSE
fa_test_generator-0.1.3.dist-info/METADATA
fa_test_generator-0.1.3.dist-info/WHEEL
fa_test_generator-0.1.3.dist-info/RECORD
