Metadata-Version: 2.3
Name: fa-test-generator
Version: 0.1.3
Summary: Utility for generating tests for FastAPI routers and endpoints
License: MIT
Author: eac0de
Author-email: egor2001zhukov@gmail.com
Requires-Python: >=3.12
Classifier: License :: OSI Approved :: MIT License
Classifier: Programming Language :: Python :: 3
Classifier: Programming Language :: Python :: 3.12
Classifier: Programming Language :: Python :: 3.13
Requires-Dist: asgi-lifespan (>=2.1.0,<3.0.0)
Requires-Dist: fastapi (>=0.115.6,<0.116.0)
Requires-Dist: httpx (>=0.28.1,<0.29.0)
Requires-Dist: jsony (>=0.1.0,<0.2.0)
Requires-Dist: pytest (>=8.3.4,<9.0.0)
Requires-Dist: pytest-asyncio (>=0.25.2,<0.26.0)
Requires-Dist: pytest-dotenv (>=0.5.2,<0.6.0)
